LICENSE
README.md
setup.cfg
setup.py
spacy_dbpedia_spotlight/__init__.py
spacy_dbpedia_spotlight/entity_linker.py
spacy_dbpedia_spotlight/util.py
spacy_dbpedia_spotlight.egg-info/PKG-INFO
spacy_dbpedia_spotlight.egg-info/SOURCES.txt
spacy_dbpedia_spotlight.egg-info/dependency_links.txt
spacy_dbpedia_spotlight.egg-info/entry_points.txt
spacy_dbpedia_spotlight.egg-info/requires.txt
spacy_dbpedia_spotlight.egg-info/top_level.txt