Metadata-Version: 2.1
Name: spacy-dbpedia-spotlight
Version: 0.2.6
Summary: SpaCy DBpedia Spotlight wrapper
Home-page: https://github.com/MartinoMensio/spacy-dbpedia-spotlight
Author: Martino Mensio
Author-email: martino.mensio@open.ac.uk
License-File: LICENSE
